{
  "places": [
    {
      "name": "Golden Gate Bridge",
      "lat": 37.8199,
      "lng": -122.4783,
      "description": "A famous suspension bridge in San Francisco."
    },
    {
      "name": "Alcatraz Island",
      "lat": 37.8267,
      "lng": -122.423,
      "description": "Historic island with a former prison."
    },
    {
      "name": "Aasee Bocholt",
      "lat": 51.83164049985181,
      "lng": 6.632480621337891,
      "description": "Nice place, biatch"
    },
    {
      "name": "sfdf",
      "lat": 6,
      "lng": 5,
      "description": "sdfs"
    },
    {
      "name": "d",
      "lat": 5,
      "lng": 6,
      "description": "d"
    },
    {
      "name": "sdf",
      "lat": 51.8381005055281,
      "lng": 6.547679901123047,
      "description": "sdf"
    },
    {
      "name": "ggg",
      "lat": 51.833219308608214,
      "lng": 6.555747985839844,
      "description": "gggg"
    },
    {
      "name": "hköhkb",
      "lat": 51.83214690002738,
      "lng": 6.65522575378418,
      "description": "izfd6urs5ushg"
    },
    {
      "name": "Maliniis House",
      "lat": 51.858474987895654,
      "lng": 6.652361154556275,
      "description": "Very gud for lighting JOINT because Malin like smokin"
    },
    {
      "name": "sfg",
      "lat": 51.84723190178549,
      "lng": 6.653423309326173,
      "description": "dfg"
    }
  ]
}